[{"model": "mailing.message", "pk": 1, "fields": {"subject_of_letter": "тест темы", "body_of_letter": "тест тела", "creator": 3}}, {"model": "mailing.message", "pk": 2, "fields": {"subject_of_letter": "новое", "body_of_letter": "новое", "creator": 1}}, {"model": "mailing.message", "pk": 3, "fields": {"subject_of_letter": "123456", "body_of_letter": "`1233", "creator": null}}, {"model": "mailing.customer", "pk": 1, "fields": {"contact_email": "groninger.official@yandex.ru", "last_name": "тест фамилии", "first_name": "тест имени", "patronymic": "тест отчества", "comment": "тест комментария", "creator": 3}}, {"model": "mailing.customer", "pk": 2, "fields": {"contact_email": "novoe@yandex.ru", "last_name": "новое", "first_name": "новое", "patronymic": "новое", "comment": "новое", "creator": 1}}, {"model": "mailing.customer", "pk": 3, "fields": {"contact_email": "gfdgnfdgfd@yandex.ru", "last_name": "gfd", "first_name": "gfdgfd", "patronymic": "gfdgfd", "comment": "gfdgfdg", "creator": null}}, {"model": "mailing.periodicity", "pk": 1, "fields": {"name": "раз в день"}}, {"model": "mailing.mailing", "pk": 1, "fields": {"name": "тест рассылки", "date_and_time_of_first_mailing": "2024-09-01T13:15:02Z", "periodicity": 1, "mailing_status": "создана", "message": 1, "mailing_start_date": "2023-01-09", "mailing_end_date": "2024-12-21", "time_which_newsletter_sent": 12, "minute_when_newsletter_should_sent": 12, "date_letter_was_sent": "2024-10-01", "active": false, "creator": 3, "customers_of_service": [1]}}, {"model": "mailing.mailing", "pk": 2, "fields": {"name": "gfgfdgf", "date_and_time_of_first_mailing": "2024-09-02T12:20:01Z", "periodicity": 1, "mailing_status": "создана", "message": 1, "mailing_start_date": "2023-01-09", "mailing_end_date": "2024-12-21", "time_which_newsletter_sent": 12, "minute_when_newsletter_should_sent": 12, "date_letter_was_sent": "2024-10-02", "active": true, "creator": null, "customers_of_service": [1, 2]}}, {"model": "mailing.mailing", "pk": 3, "fields": {"name": "gfdgfd", "date_and_time_of_first_mailing": "2024-09-04T18:53:02Z", "periodicity": 1, "mailing_status": "создана", "message": 1, "mailing_start_date": "2023-01-09", "mailing_end_date": "2024-12-21", "time_which_newsletter_sent": 1, "minute_when_newsletter_should_sent": 1, "date_letter_was_sent": "2024-10-04", "active": true, "creator": null, "customers_of_service": []}}, {"model": "mailing.attempt", "pk": 1, "fields": {"date_and_time_of_last_mailing_attempt": "2024-09-01T13:15:03Z", "mailing": 1, "attempt_status": "['groninger.official@yandex.ru - письмо отправлено']"}}, {"model": "mailing.attempt", "pk": 2, "fields": {"date_and_time_of_last_mailing_attempt": "2024-09-02T12:20:04Z", "mailing": 2, "attempt_status": "['groninger.official@yandex.ru - письмо отправлено', 'novoe@yandex.ru - письмо отправлено']"}}, {"model": "mailing.attempt", "pk": 3, "fields": {"date_and_time_of_last_mailing_attempt": "2024-09-04T18:53:02Z", "mailing": 3, "attempt_status": "[]"}}]